pinto/__init__.py
pinto/__main__.py
pinto/_version.py
pinto/cli.py
pinto/tools.py
pinto-0.1.4.dist-info/LICENSE
pinto-0.1.4.dist-info/METADATA
pinto-0.1.4.dist-info/WHEEL
pinto-0.1.4.dist-info/entry_points.txt
pinto-0.1.4.dist-info/top_level.txt
pinto-0.1.4.dist-info/RECORD
