Metadata-Version: 2.1
Name: pinto
Version: 0.1.4
Summary: Supercharged command line interface for Beancount.
Home-page: https://github.com/SeanDS/pinto
Author: Sean Leavey
Author-email: github@attackllama.com
License: GPL
Platform: UNKNOWN
Classifier: Development Status :: 3 - Alpha
Classifier: License :: OSI Approved :: GNU General Public License v3 or later (GPLv3+)
Classifier: Natural Language :: English
Classifier: Programming Language :: Python :: 3
Classifier: Programming Language :: Python :: 3.7
Requires-Python: >=3.7
Requires-Dist: beancount
Requires-Dist: click
Requires-Dist: maya
Requires-Dist: pyyaml
Requires-Dist: fuzzywuzzy[speedup]
Provides-Extra: dev
Requires-Dist: black ; extra == 'dev'
Requires-Dist: pre-commit ; extra == 'dev'
Requires-Dist: flake8 ; extra == 'dev'
Requires-Dist: readme-renderer ; extra == 'dev'
